opencrawler-1.0.2.dist-info/licenses/LICENSE
webscraper/__init__.py
webscraper/cli.py
webscraper/cli_advanced.py
webscraper/config.yaml
webscraper/worker.py
opencrawler-1.0.2.dist-info/METADATA
opencrawler-1.0.2.dist-info/WHEEL
opencrawler-1.0.2.dist-info/entry_points.txt
opencrawler-1.0.2.dist-info/top_level.txt
opencrawler-1.0.2.dist-info/RECORD
