Metadata-Version: 2.4
Name: opencrawler
Version: 1.0.2
Summary: Production-ready, enterprise-grade web scraping and crawling framework with advanced AI integration
Author-email: Nik Jois <nikjois@llamasearch.ai>
Maintainer-email: Nik Jois <nikjois@llamasearch.ai>
License: MIT
Project-URL: Homepage, https://github.com/llamasearch/opencrawler
Project-URL: Documentation, https://github.com/llamasearch/opencrawler/docs
Project-URL: Repository, https://github.com/llamasearch/opencrawler
Project-URL: Issues, https://github.com/llamasearch/opencrawler/issues
Project-URL: Changelog, https://github.com/llamasearch/opencrawler/blob/main/CHANGELOG.md
Keywords: web-scraping,crawling,ai,llm,automation,data-extraction,playwright,selenium,fastapi,microservices,enterprise,production
Classifier: Development Status :: 5 - Production/Stable
Classifier: Intended Audience :: Developers
Classifier: Intended Audience :: Information Technology
Classifier: License :: OSI Approved :: MIT License
Classifier: Operating System :: OS Independent
Classifier: Programming Language :: Python :: 3
Classifier: Programming Language :: Python :: 3.8
Classifier: Programming Language :: Python :: 3.9
Classifier: Programming Language :: Python :: 3.10
Classifier: Programming Language :: Python :: 3.11
Classifier: Programming Language :: Python :: 3.12
Classifier: Programming Language :: Python :: 3 :: Only
Classifier: Topic :: Internet :: WWW/HTTP :: Indexing/Search
Classifier: Topic :: Software Development :: Libraries :: Python Modules
Classifier: Topic :: Scientific/Engineering :: Artificial Intelligence
Classifier: Topic :: System :: Distributed Computing
Classifier: Framework :: FastAPI
Classifier: Framework :: AsyncIO
Classifier: Environment :: Web Environment
Classifier: Typing :: Typed
Requires-Python: >=3.8
License-File: LICENSE
Requires-Dist: fastapi>=0.104.0
Requires-Dist: uvicorn[standard]>=0.24.0
Requires-Dist: pydantic>=2.5.0
Requires-Dist: aiohttp>=3.9.0
Requires-Dist: playwright>=1.40.0
Requires-Dist: selenium>=4.15.0
Requires-Dist: requests>=2.31.0
Requires-Dist: cloudscraper>=1.2.71
Requires-Dist: beautifulsoup4>=4.12.0
Requires-Dist: lxml>=4.9.0
Requires-Dist: asyncpg>=0.29.0
Requires-Dist: redis>=5.0.0
Requires-Dist: prometheus-client>=0.19.0
Requires-Dist: psutil>=5.9.0
Requires-Dist: rich>=13.7.0
Requires-Dist: typer>=0.9.0
Requires-Dist: pyyaml>=6.0.1
Requires-Dist: jinja2>=3.1.0
Requires-Dist: python-multipart>=0.0.6
Requires-Dist: httpx>=0.25.0
Requires-Dist: asyncio-mqtt>=0.13.0
Requires-Dist: structlog>=23.2.0
Requires-Dist: tenacity>=8.2.0
Requires-Dist: python-jose[cryptography]>=3.3.0
Requires-Dist: passlib[bcrypt]>=1.7.4
Requires-Dist: python-dotenv>=1.0.0
Requires-Dist: click>=8.1.0
Requires-Dist: jsonschema>=4.20.0
Requires-Dist: markupsafe>=2.1.0
Requires-Dist: certifi>=2023.11.17
Provides-Extra: ai
Requires-Dist: openai>=1.3.0; extra == "ai"
Requires-Dist: anthropic>=0.7.0; extra == "ai"
Requires-Dist: tiktoken>=0.5.0; extra == "ai"
Requires-Dist: transformers>=4.35.0; extra == "ai"
Requires-Dist: torch>=2.1.0; extra == "ai"
Requires-Dist: sentence-transformers>=2.2.0; extra == "ai"
Provides-Extra: dev
Requires-Dist: pytest>=7.4.0; extra == "dev"
Requires-Dist: pytest-asyncio>=0.21.0; extra == "dev"
Requires-Dist: pytest-cov>=4.1.0; extra == "dev"
Requires-Dist: pytest-mock>=3.12.0; extra == "dev"
Requires-Dist: black>=23.11.0; extra == "dev"
Requires-Dist: flake8>=6.1.0; extra == "dev"
Requires-Dist: mypy>=1.7.0; extra == "dev"
Requires-Dist: pre-commit>=3.5.0; extra == "dev"
Requires-Dist: coverage>=7.3.0; extra == "dev"
Requires-Dist: bandit>=1.7.5; extra == "dev"
Requires-Dist: safety>=2.3.0; extra == "dev"
Requires-Dist: isort>=5.12.0; extra == "dev"
Requires-Dist: pylint>=3.0.0; extra == "dev"
Requires-Dist: sphinx>=7.2.0; extra == "dev"
Requires-Dist: sphinx-rtd-theme>=1.3.0; extra == "dev"
Provides-Extra: database
Requires-Dist: asyncpg>=0.29.0; extra == "database"
Requires-Dist: psycopg2-binary>=2.9.9; extra == "database"
Requires-Dist: sqlalchemy[asyncio]>=2.0.0; extra == "database"
Requires-Dist: alembic>=1.13.0; extra == "database"
Requires-Dist: redis>=5.0.0; extra == "database"
Provides-Extra: monitoring
Requires-Dist: prometheus-client>=0.19.0; extra == "monitoring"
Requires-Dist: grafana-client>=3.2.0; extra == "monitoring"
Requires-Dist: statsd>=4.0.1; extra == "monitoring"
Requires-Dist: datadog>=0.48.0; extra == "monitoring"
Provides-Extra: cloud
Requires-Dist: boto3>=1.34.0; extra == "cloud"
Requires-Dist: google-cloud-storage>=2.10.0; extra == "cloud"
Requires-Dist: azure-storage-blob>=12.19.0; extra == "cloud"
Requires-Dist: kubernetes>=28.1.0; extra == "cloud"
Provides-Extra: all
Requires-Dist: opencrawler[ai,cloud,database,dev,monitoring]; extra == "all"
Dynamic: license-file
